anansi/__init__.py
anansi/_version.py
anansi/cli.py
anansi/exceptions.py
anansi/actions/__init__.py
anansi/actions/collection.py
anansi/actions/model.py
anansi/actions/storage.py
anansi/core/__init__.py
anansi/core/abstract_storage.py
anansi/core/collection.py
anansi/core/collector.py
anansi/core/context.py
anansi/core/decorators.py
anansi/core/field.py
anansi/core/index.py
anansi/core/middleware.py
anansi/core/model.py
anansi/core/model_type.py
anansi/core/query.py
anansi/core/query_group.py
anansi/core/reference.py
anansi/core/schema.py
anansi/core/store.py
anansi/fields/__init__.py
anansi/fields/blobs.py
anansi/fields/boolean.py
anansi/fields/dates.py
anansi/fields/numbers.py
anansi/fields/strings.py
anansi/middleware/__init__.py
anansi/middleware/storage.py
anansi/server/__init__.py
anansi/server/factories.py
anansi/server/request_helpers.py
anansi/server/resources.py
anansi/server/server.py
anansi/storage/__init__.py
anansi/storage/sql/__init__.py
anansi/storage/sql/abstract.py
anansi/storage/sql/postgres.py
anansi/storage/sql/utils.py
anansi/utils/__init__.py
anansi/utils/enums.py
anansi/utils/json.py
anansi/utils/misc.py
anansi-0.0.dev55.dist-info/DESCRIPTION.rst
anansi-0.0.dev55.dist-info/METADATA
anansi-0.0.dev55.dist-info/RECORD
anansi-0.0.dev55.dist-info/WHEEL
anansi-0.0.dev55.dist-info/entry_points.txt
anansi-0.0.dev55.dist-info/metadata.json
anansi-0.0.dev55.dist-info/top_level.txt
