Metadata-Version: 2.0
Name: anansi
Version: 0.0.dev55
Summary: Asyncio data modeling library
Home-page: https://github.com/anansi-framework/anansi
Author: eric.hulser@gmail.com
Author-email: eric.hulser@gmail.com
License: MIT
Platform: UNKNOWN
Requires-Dist: async-generator
Requires-Dist: contextvars
Requires-Dist: dotted
Requires-Dist: inflection
Requires-Dist: pyyaml
Provides-Extra: aiohttp
Provides-Extra: dev
Provides-Extra: postgres
